courriers/__init__.py
courriers/admin.py
courriers/base_models.py
courriers/compat.py
courriers/forms.py
courriers/settings.py
courriers/signals.py
courriers/tasks.py
courriers/urls.py
courriers/utils.py
courriers/views.py
courriers/backends/__init__.py
courriers/backends/base.py
courriers/backends/campaign.py
courriers/backends/mailjet_rest.py
courriers/backends/simple.py
courriers/locale/de/LC_MESSAGES/django.mo
courriers/locale/de/LC_MESSAGES/django.po
courriers/locale/en/LC_MESSAGES/django.mo
courriers/locale/en/LC_MESSAGES/django.po
courriers/locale/fr/LC_MESSAGES/django.mo
courriers/locale/fr/LC_MESSAGES/django.po
courriers/management/__init__.py
courriers/management/commands/__init__.py
courriers/migrations/0001_initial.py
courriers/migrations/__init__.py
courriers/models/__init__.py
courriers/models/newsletter.py
courriers/models/newsletteritem.py
courriers/models/newsletterlist.py
courriers/models/newslettersegment.py
courriers/templates/admin/courriers/newsletter/change_form.html
courriers/templates/courriers/newsletter_detail.html
courriers/templates/courriers/newsletter_list.html
courriers/templates/courriers/newsletter_list_subscribe_done.html
courriers/templates/courriers/newsletter_list_subscribe_form.html
courriers/templates/courriers/newsletter_list_unsubscribe.html
courriers/templates/courriers/newsletter_list_unsubscribe_done.html
courriers/templates/courriers/newsletter_raw_detail.html
courriers/templates/courriers/newsletter_raw_detail.txt
courriers/tests/__init__.py
courriers/tests/celery.py
courriers/tests/models.py
courriers/tests/settings.py
courriers/tests/tests.py
courriers/tests/migrations/0001_initial.py
courriers/tests/migrations/__init__.py
django_courriers-0.9.1.dist-info/AUTHORS.rst
django_courriers-0.9.1.dist-info/LICENSE
django_courriers-0.9.1.dist-info/METADATA
django_courriers-0.9.1.dist-info/WHEEL
django_courriers-0.9.1.dist-info/top_level.txt
django_courriers-0.9.1.dist-info/RECORD
